{
  "title": "A Colder War",
  "episodeNumber": 8.5,
  "publishDate": "2022-11-09T00:00:00.000Z",
  "description": "Halloween Special Part 2: the 2000 story by Charles Stross.",
  "audioUrl": "https://anchor.fm/s/9ebdf594/podcast/play/60116213/https%3A%2F%2Fd3ctxlq1ktw2nl.cloudfront.net%2Fstaging%2F2022-10-9%2F295845206-44100-2-f0305b758ea11.m4a",
  "storyUrl": "http://www.infinityplus.co.uk/stories/colderwar.htm",
  "featuredStory": {
    "title": "A Colder War",
    "author": "Charles Stross",
    "year": 2000
  },
  "duration": "00:13:37",
  "image": "../../assets/images/episode_0085.jpg"
}
